retry.py
retry.it-1.2.dist-info/DESCRIPTION.rst
retry.it-1.2.dist-info/METADATA
retry.it-1.2.dist-info/RECORD
retry.it-1.2.dist-info/WHEEL
retry.it-1.2.dist-info/metadata.json
retry.it-1.2.dist-info/top_level.txt
