Metadata-Version: 2.0
Name: retry.it
Version: 1.2
Summary: A small and simple library to retry functions
Home-page: https://github.com/seemethere/retry
Author: Eli Uriegas
Author-email: seemethere101@gmail.com
License: MIT
Platform: UNKNOWN
Classifier: Programming Language :: Python :: 2
Classifier: Programming Language :: Python :: 3
Classifier: Intended Audience :: Developers
Classifier: License :: OSI Approved :: MIT License
Classifier: Topic :: Software Development :: Libraries
Classifier: Topic :: Utilities
Requires-Dist: decorator
